scenarioselector/__init__.py
scenarioselector/exceptions.py
scenarioselector/graphics.py
scenarioselector/pivot_rule.py
scenarioselector/pivot_scenarios.py
scenarioselector/pivot_variable.py
scenarioselector/scenario_selector.py
scenarioselector-0.1.4.dist-info/LICENSE
scenarioselector-0.1.4.dist-info/METADATA
scenarioselector-0.1.4.dist-info/WHEEL
scenarioselector-0.1.4.dist-info/top_level.txt
scenarioselector-0.1.4.dist-info/RECORD
