Metadata-Version: 2.1
Name: scenarioselector
Version: 0.1.4
Summary: The scenario selection algorithm selects a maximal subset of scenarios from a scenario set, so that the selected scenarios have specified means (or sums).
Home-page: https://github.com/markpowen/ScenarioSelectorPython
Author: Mark Philip Owen
Author-email: mark.p.owen@gmail.com
License: UNKNOWN
Project-URL: Bug Tracker, https://github.com/markpowen/ScenarioSelectorPython/issues
Platform: UNKNOWN
Classifier: Intended Audience :: Science/Research
Classifier: Programming Language :: Python :: 3
Classifier: License :: OSI Approved :: Apache Software License
Classifier: Operating System :: OS Independent
Classifier: Topic :: Scientific/Engineering
Requires-Python: >=3.7.1
Requires-Dist: numpy (>=1.18.0)
Requires-Dist: pandas (>=1.0.0)
